mmg_toolbox/__init__.py
mmg_toolbox/__main__.py
mmg_toolbox/beamline_metadata/__init__.py
mmg_toolbox/beamline_metadata/config.py
mmg_toolbox/beamline_metadata/hdfmap_generic.py
mmg_toolbox/beamline_metadata/metadata_strings.py
mmg_toolbox/data/xray_edges.json
mmg_toolbox/diffraction/__init__.py
mmg_toolbox/diffraction/diffcalc.py
mmg_toolbox/diffraction/lattice.py
mmg_toolbox/diffraction/msmapper.py
mmg_toolbox/fitting/__init__.py
mmg_toolbox/fitting/fit_functions.py
mmg_toolbox/fitting/functions.py
mmg_toolbox/fitting/manager.py
mmg_toolbox/fitting/models.py
mmg_toolbox/fitting/results.py
mmg_toolbox/nexus/__init__.py
mmg_toolbox/nexus/instrument_model.py
mmg_toolbox/nexus/nexus_functions.py
mmg_toolbox/nexus/nexus_names.py
mmg_toolbox/nexus/nexus_reader.py
mmg_toolbox/nexus/nexus_scan.py
mmg_toolbox/nexus/nexus_transformations.py
mmg_toolbox/nexus/nexus_writer.py
mmg_toolbox/plotting/__init__.py
mmg_toolbox/plotting/exp_plot_manager.py
mmg_toolbox/plotting/matplotlib.py
mmg_toolbox/plotting/scan_plot_manager.py
mmg_toolbox/scripts/__init__.py
mmg_toolbox/scripts/example_script.py
mmg_toolbox/scripts/experiment_fitting.py
mmg_toolbox/scripts/experiment_multiline.py
mmg_toolbox/scripts/scripts.py
mmg_toolbox/scripts/spectra_script.py
mmg_toolbox/tkguis/__init__.py
mmg_toolbox/tkguis/__main__.py
mmg_toolbox/tkguis/cli.py
mmg_toolbox/tkguis/experiment_management.py
mmg_toolbox/tkguis/apps/__init__.py
mmg_toolbox/tkguis/apps/config_editor.py
mmg_toolbox/tkguis/apps/data_viewer.py
mmg_toolbox/tkguis/apps/edit_text.py
mmg_toolbox/tkguis/apps/experiment.py
mmg_toolbox/tkguis/apps/file_browser.py
mmg_toolbox/tkguis/apps/log_viewer.py
mmg_toolbox/tkguis/apps/multi_scan_analysis.py
mmg_toolbox/tkguis/apps/namespace_select.py
mmg_toolbox/tkguis/apps/nexus.py
mmg_toolbox/tkguis/apps/peak_fit_analysis.py
mmg_toolbox/tkguis/apps/python_editor.py
mmg_toolbox/tkguis/apps/scans.py
mmg_toolbox/tkguis/apps/script_runner.py
mmg_toolbox/tkguis/apps/visit_viewer.py
mmg_toolbox-0.5.1.dist-info/licenses/LICENSE
mmg_toolbox-0.5.1.dist-info/METADATA
mmg_toolbox-0.5.1.dist-info/WHEEL
mmg_toolbox-0.5.1.dist-info/entry_points.txt
mmg_toolbox-0.5.1.dist-info/top_level.txt
mmg_toolbox-0.5.1.dist-info/RECORD
