Metadata-Version: 2.4
Name: mmg_toolbox
Version: 0.5.1
Summary: Repository for useful python data analysis functions for the Diamond Magnetic Materials Group
Author-email: Dan Porter <dan.porter@diamond.ac.uk>
Maintainer-email: Dan Porter <dan.porter@diamond.ac.uk>
License:                                  Apache License
Keywords: nexus
Classifier: Programming Language :: Python :: 3.10
Classifier: Intended Audience :: Science/Research
Classifier: Topic :: Scientific/Engineering :: Physics
Classifier: License :: OSI Approved :: Apache Software License
Classifier: Development Status :: 3 - Alpha
Requires-Python: >=3.10
License-File: LICENSE
Requires-Dist: numpy
Requires-Dist: h5py
Requires-Dist: hdf5plugin
Requires-Dist: hdfmap>=1.1.0
Requires-Dist: matplotlib
Requires-Dist: imageio
Requires-Dist: scipy
Requires-Dist: lmfit
Requires-Dist: stomp.py
Requires-Dist: diffcalc-core
Provides-Extra: base
Requires-Dist: numpy; extra == "base"
Requires-Dist: h5py; extra == "base"
Requires-Dist: hdf5plugin; extra == "base"
Requires-Dist: hdfmap>=1.1.0; extra == "base"
Requires-Dist: matplotlib; extra == "base"
Requires-Dist: imageio; extra == "base"
Requires-Dist: lmfit; extra == "base"
Provides-Extra: full
Requires-Dist: numpy; extra == "full"
Requires-Dist: h5py; extra == "full"
Requires-Dist: hdf5plugin; extra == "full"
Requires-Dist: hdfmap>=1.1.0; extra == "full"
Requires-Dist: matplotlib; extra == "full"
Requires-Dist: imageio; extra == "full"
Requires-Dist: scipy; extra == "full"
Requires-Dist: lmfit; extra == "full"
Requires-Dist: diffcalc-core; extra == "full"
Requires-Dist: ipython; extra == "full"
Requires-Dist: jupyter; extra == "full"
Requires-Dist: nbconvert; extra == "full"
Requires-Dist: nbformat; extra == "full"
Requires-Dist: nexpy; extra == "full"
Dynamic: license-file
